pyeditdistance/__init__.py
pyeditdistance/distance.py
pyeditdistance-1.0.1.dist-info/METADATA
pyeditdistance-1.0.1.dist-info/WHEEL
pyeditdistance-1.0.1.dist-info/licenses/LICENSE
pyeditdistance-1.0.1.dist-info/RECORD
