Metadata-Version: 2.1
Name: pyeditdistance
Version: 1.0.1
Summary: A pure, minimalist, no-dependency Python library of various edit distances.
Project-URL: Homepage, https://github.com/cgshep/pyeditdistance
Project-URL: Bug Tracker, https://github.com/cgshep/pyeditdistance/issues
Author-email: Carlton Shepherd <carlton@linux.com>
Classifier: Development Status :: 4 - Beta
Classifier: Intended Audience :: Developers
Classifier: Intended Audience :: Information Technology
Classifier: Intended Audience :: Science/Research
Classifier: License :: OSI Approved :: MIT License
Classifier: Operating System :: OS Independent
Classifier: Programming Language :: Python :: 3
Classifier: Topic :: Scientific/Engineering :: Artificial Intelligence
Classifier: Topic :: Scientific/Engineering :: Information Analysis
Classifier: Topic :: Text Processing
Requires-Python: >=3.7
